{
    "name": "flare",
    "children": [
     {
      "name": "Alaska",
      "children": [
       {
        "name": "Denali National Park and Preserve",
        "children": [
         {"name": "Endangered", "value": 0},
         {"name": "In Recovery", "value": 0},
         {"name": "No Concern", "value": 1288},
         
         {"name": "Species of Concern", "value": 30},
         {"name": "Threatened", "value": 1},
         {"name": "Under Review", "value": 1}
        ]
       },
       {
        "name": "Gates Of The Arctic National Park and Preserve",
        "children": [
            {"name": "Endangered", "value": 0},
          
            {"name": "In Recovery", "value": 0},
            {"name": "No Concern", "value": 1332},
            
            {"name": "Species of Concern", "value": 21},
            {"name": "Threatened", "value": 0},
            {"name": "Under Review", "value": 0}
        ]
       },
       {
        "name": "Glacier Bay National Park and Preserve",
        "children": [
            {"name": "Endangered", "value": 9},
           
            {"name": "In Recovery", "value": 1},
            {"name": "No Concern", "value": 1896},
          
            {"name": "Species of Concern", "value": 47},
            {"name": "Threatened", "value": 3},
            {"name": "Under Review", "value": 1}
        ]
       },
       {
        "name": "Katmai National Park and Preserve",
        "children": [
            {"name": "Endangered", "value": 6},
            
            {"name": "In Recovery", "value": 0},
            {"name": "No Concern", "value": 1184},
           
            {"name": "Species of Concern", "value": 31},
            {"name": "Threatened", "value": 2},
            {"name": "Under Review", "value": 2}
        ]
       },
       {
        "name": "Kenai Fjords National Park",
        "children": [
            {"name": "Endangered", "value": 8},
           
            {"name": "In Recovery", "value": 0},
            {"name": "No Concern", "value": 1009},
           
            {"name": "Species of Concern", "value": 36},
            {"name": "Threatened", "value": 2},
            {"name": "Under Review", "value": 2}
        ]
       },
       {
        "name": "Kobuk Valley National Park",
        "children": [
            {"name": "Endangered", "value": 0},
           
            {"name": "In Recovery", "value": 0},
            {"name": "No Concern", "value": 1002},
          
            {"name": "Species of Concern", "value": 22},
            {"name": "Threatened", "value": 1},
            {"name": "Under Review", "value": 0}
        ]
       },
       {
        "name": "Wrangell - St Elias National Park and Preserve",
        "children": [
            {"name": "Endangered", "value": 5},
           
            {"name": "In Recovery", "value": 1},
            {"name": "No Concern", "value": 1745},
          
            {"name": "Species of Concern", "value": 40},
            {"name": "Threatened", "value": 3},
            {"name": "Under Review", "value": 2}
        ]
       }
      ]
     },
     {
      "name": "Intermountain",
      "children": [
        {
            "name": "Arches National Park",
            "children": [
                {"name": "Endangered", "value": 2},
              
                {"name": "In Recovery", "value": 1},
                {"name": "No Concern", "value": 973},
               
                {"name": "Species of Concern", "value": 69},
                {"name": "Threatened", "value": 2},
                {"name": "Under Review", "value": 1}
            ]
           },
           {
            "name": "Big Bend National Park",
            "children": [
                {"name": "Endangered", "value": 11},
                {"name": "In Recovery", "value": 2},
                {"name": "No Concern", "value": 2131},
            
                {"name": "Species of Concern", "value": 116},
                {"name": "Threatened", "value": 5},
                {"name": "Under Review", "value": 4}
            ]
           },
           {
            "name": "Black Canyon of the Gunnison National Park",
            "children": [
                {"name": "Endangered", "value": 2},
                {"name": "In Recovery", "value": 1},
                {"name": "No Concern", "value": 1040},
               
                {"name": "Species of Concern", "value": 61},
                {"name": "Threatened", "value": 1},
                {"name": "Under Review", "value": 1}
            ]
           },
           {
            "name": "Bryce Canyon National Park",
            "children": [
                {"name": "Endangered", "value": 2},
                {"name": "In Recovery", "value": 1},
                {"name": "No Concern", "value": 1213},
                
                {"name": "Species of Concern", "value": 69},
                {"name": "Threatened", "value": 1},
                {"name": "Under Review", "value": 0}
            ]
           },
           {
            "name": "Canyonlands National Park",
            "children": [
                {"name": "Endangered", "value": 7},
                {"name": "In Recovery", "value": 1},
                {"name": "No Concern", "value": 1143},
            
                {"name": "Species of Concern", "value": 69},
                {"name": "Threatened", "value": 3},
                {"name": "Under Review", "value": 0}
            ]
           },
           {
            "name": "Capitol Reef National Park",
            "children": [
                {"name": "Endangered", "value": 6},
                {"name": "In Recovery", "value": 2},
                {"name": "No Concern", "value": 1473},
              
                {"name": "Species of Concern", "value": 80},
                {"name": "Threatened", "value": 5},
                {"name": "Under Review", "value": 0}
            ]
           },
           {
            "name": "Glacier National Park",
            "children": [
                {"name": "Endangered", "value": 0},
                {"name": "In Recovery", "value": 2},
                {"name": "No Concern", "value": 2473},
               
                {"name": "Species of Concern", "value": 75},
                {"name": "Threatened", "value": 2},
                {"name": "Under Review", "value": 4}
            ]
           },
           {
            "name": "Grand Canyon National Park",
            "children": [
                {"name": "Endangered", "value": 11},
                {"name": "In Recovery", "value": 3},
                {"name": "No Concern", "value": 2487},
               
                {"name": "Species of Concern", "value": 114},
                {"name": "Threatened", "value": 4},
                {"name": "Under Review", "value": 3}
            ]
           },
           {
            "name": "Grand Teton National Park",
            "children": [
                {"name": "Endangered", "value": 3},
                {"name": "In Recovery", "value": 2},
                {"name": "No Concern", "value": 1944},
               
                {"name": "Species of Concern", "value": 77},
                {"name": "Threatened", "value": 1},
                {"name": "Under Review", "value": 3}
            ]
           },
           {
            "name": "Great Sand Dunes National Park and Preserve",
            "children": [
                {"name": "Endangered", "value": 0},
                {"name": "In Recovery", "value": 1},
                {"name": "No Concern", "value": 892},
              
                {"name": "Species of Concern", "value": 59},
                {"name": "Threatened", "value": 0},
                {"name": "Under Review", "value": 0}
            ]
           },
           {
            "name": "Guadalupe Mountains National Park",
            "children": [
                {"name": "Endangered", "value": 2},
                {"name": "In Recovery", "value": 1},
                {"name": "No Concern", "value": 1655},
                
                {"name": "Species of Concern", "value": 83},
                {"name": "Threatened", "value": 2},
                {"name": "Under Review", "value": 2}
            ]
           },
           {
            "name": "Mesa Verde National Park",
            "children": [
                {"name": "Endangered", "value": 6},
                {"name": "In Recovery", "value": 1},
                {"name": "No Concern", "value": 1153},
                
                {"name": "Species of Concern", "value": 78},
                {"name": "Threatened", "value": 4},
                {"name": "Under Review", "value": 1}
            ]
           },
           {
            "name": "Petrified Forest National Park",
            "children": [
                {"name": "Endangered", "value": 4},
                {"name": "In Recovery", "value": 2},
                {"name": "No Concern", "value": 772},
               
                {"name": "Species of Concern", "value": 74},
                {"name": "Threatened", "value": 1},
                {"name": "Under Review", "value": 0}
            ]
           }
      ]
     },
     {
      "name": "Midwest",
      "children": [
        {
            "name": "Badlands National Park",
            "children": [
                {"name": "Endangered", "value": 2},
                {"name": "In Recovery", "value": 1},
                {"name": "No Concern", "value": 1320},
                
                {"name": "Species of Concern", "value": 62},
                {"name": "Threatened", "value": 1},
                {"name": "Under Review", "value": 3}
            ]
           },
           {
            "name": "Cuyahoga Valley National Park",
            "children": [
                {"name": "Endangered", "value": 1},
                {"name": "In Recovery", "value": 1},
                {"name": "No Concern", "value": 1880},
               
                {"name": "Species of Concern", "value": 52},
                {"name": "Threatened", "value": 1},
                {"name": "Under Review", "value": 5}
            ]
           },
           {
            "name": "Hot Springs National Park",
            "children": [
                {"name": "Endangered", "value": 4},
                {"name": "In Recovery", "value": 1},
                {"name": "No Concern", "value": 1877},
               
                {"name": "Species of Concern", "value": 61},
                {"name": "Threatened", "value": 2},
                {"name": "Under Review", "value": 5}
            ]
           },
           {
            "name": "Isle Royale National Park",
            "children": [
                {"name": "Endangered", "value": 2},
                {"name": "In Recovery", "value": 1},
                {"name": "No Concern", "value": 1332},
                
                {"name": "Species of Concern", "value": 58},
                {"name": "Threatened", "value": 2},
                {"name": "Under Review", "value": 2}
            ]
           },
           {
            "name": "Theodore Roosevelt National Park",
            "children": [
                {"name": "Endangered", "value": 3},
                {"name": "In Recovery", "value": 1},
                {"name": "No Concern", "value": 1110},
               
                {"name": "Species of Concern", "value": 49},
                {"name": "Threatened", "value": 1},
                {"name": "Under Review", "value": 1}
            ]
           },
           {
            "name": "Voyageurs National Park",
            "children": [
                {"name": "Endangered", "value": 1},
                {"name": "In Recovery", "value": 1},
                {"name": "No Concern", "value": 1395},
              
                {"name": "Species of Concern", "value": 52},
                {"name": "Threatened", "value": 2},
                {"name": "Under Review", "value": 2}
            ]
           },
           {
            "name": "Wind Cave National Park",
            "children": [
                {"name": "Endangered", "value": 3},
                {"name": "In Recovery", "value": 1},
                {"name": "No Concern", "value": 1325},
               
                {"name": "Species of Concern", "value": 63},
                {"name": "Threatened", "value": 1},
                {"name": "Under Review", "value": 2}
            ]
           }
      ]
     },
     {
      "name": "Pacific-West",
      "children": [
        {
            "name": "Channel Islands National Park",
            "children": [
                {"name": "Endangered", "value": 24},
                {"name": "In Recovery", "value": 5},
                {"name": "No Concern", "value": 1741},
               
                {"name": "Species of Concern", "value": 104},
                {"name": "Threatened", "value": 8},
                {"name": "Under Review", "value": 3}
            ]
           },
           {
            "name": "Crater Lake National Park",
            "children": [
                {"name": "Endangered", "value": 4},
                {"name": "In Recovery", "value": 3},
                {"name": "No Concern", "value": 3677},
              
                {"name": "Species of Concern", "value": 66},
                {"name": "Threatened", "value": 5},
                {"name": "Under Review", "value": 4}
            ]
           },
           {
            "name": "Great Basin National Park",
            "children": [
                {"name": "Endangered", "value": 2},
                {"name": "In Recovery", "value": 1},
                {"name": "No Concern", "value": 2553},
               
                {"name": "Species of Concern", "value": 89},
                {"name": "Threatened", "value": 5},
                {"name": "Under Review", "value": 3}
            ]
           },
           {
            "name": "Joshua Tree National Park",
            "children": [
                {"name": "Endangered", "value": 6},
                {"name": "In Recovery", "value": 2},
                {"name": "No Concern", "value": 2185},
               
                {"name": "Species of Concern", "value": 97},
                {"name": "Threatened", "value": 3},
                {"name": "Under Review", "value": 1}
            ]
           },
           {
            "name": "Lassen Volcanic National Park",
            "children": [
                {"name": "Endangered", "value": 6},
                {"name": "In Recovery", "value": 2},
                {"name": "No Concern", "value": 1707},
              
                {"name": "Species of Concern", "value": 72},
                {"name": "Threatened", "value": 3},
                {"name": "Under Review", "value": 6}
            ]
           },
           {
            "name": "Mount Rainier National Park",
            "children": [
                {"name": "Endangered", "value": 1},
                {"name": "In Recovery", "value": 0},
                {"name": "No Concern", "value": 1684},
               
                {"name": "Species of Concern", "value": 47},
                {"name": "Threatened", "value": 6},
                {"name": "Under Review", "value": 5}
            ]
           },
           {
            "name": "North Cascades National Park",
            "children": [
                {"name": "Endangered", "value": 3},
                {"name": "In Recovery", "value": 1},
                {"name": "No Concern", "value": 3283},
               
                {"name": "Species of Concern", "value": 67},
                {"name": "Threatened", "value": 6},
                {"name": "Under Review", "value": 3}
            ]
           },
           {
            "name": "Olympic National Park",
            "children": [
                {"name": "Endangered", "value": 2},
                {"name": "In Recovery", "value": 3},
                {"name": "No Concern", "value": 1860},
              
                {"name": "Species of Concern", "value": 70},
                {"name": "Threatened", "value": 8},
                {"name": "Under Review", "value": 5}
            ]
           },
           {
            "name": "Pinnacles National Park",
            "children": [
                {"name": "Endangered", "value": 2},
                {"name": "In Recovery", "value": 1},
                {"name": "No Concern", "value": 1339},
               
                {"name": "Species of Concern", "value": 72},
                {"name": "Threatened", "value": 0},
                {"name": "Under Review", "value": 2}
            ]
           },
           {
            "name": "Redwood National Park",
            "children": [
                {"name": "Endangered", "value": 21},
                {"name": "In Recovery", "value": 7},
                {"name": "No Concern", "value": 6141},
               
                {"name": "Species of Concern", "value": 124},
                {"name": "Threatened", "value": 11},
                {"name": "Under Review", "value": 6}
            ]
           },
           {
            "name": "Sequoia and Kings Canyon National Parks",
            "children": [
                {"name": "Endangered", "value": 4},
                {"name": "In Recovery", "value": 1},
                {"name": "No Concern", "value": 1906},
              
                {"name": "Species of Concern", "value": 77},
                {"name": "Threatened", "value": 1},
                {"name": "Under Review", "value": 5}
            ]
           },
           {
            "name": "Yosemite National Park",
            "children": [
                {"name": "Endangered", "value": 4},
                {"name": "In Recovery", "value": 2},
                {"name": "No Concern", "value": 1992},
               
                {"name": "Species of Concern", "value": 81},
                {"name": "Threatened", "value": 5},
                {"name": "Under Review", "value": 4}
            ]
           }
      ]
     },
     {
      "name": "Southeast",
      "children": [
        {
            "name": "Biscayne National Park",
            "children": [
                {"name": "Endangered", "value": 31},
                {"name": "In Recovery", "value": 2},
                {"name": "No Concern", "value": 1661},
               
                {"name": "Species of Concern", "value": 40},
                {"name": "Threatened", "value": 8},
                {"name": "Under Review", "value": 1}
            ]
           },
           {
            "name": "Congaree National Park",
            "children": [
                {"name": "Endangered", "value": 4},
                {"name": "In Recovery", "value": 1},
                {"name": "No Concern", "value": 2272},
              
                {"name": "Species of Concern", "value": 37},
                {"name": "Threatened", "value": 1},
                {"name": "Under Review", "value":6}
            ]
           },
           {
            "name": "Dry Tortugas National Park",
            "children": [
                {"name": "Endangered", "value": 5},
                {"name": "In Recovery", "value": 1},
                {"name": "No Concern", "value": 788},
               
                {"name": "Species of Concern", "value": 46},
                {"name": "Threatened", "value": 6},
                {"name": "Under Review", "value": 2}
            ]
           },
           {
            "name": "Everglades National Park",
            "children": [
                {"name": "Endangered", "value": 16},
                {"name": "In Recovery", "value": 2},
                {"name": "No Concern", "value": 1972},
              
                {"name": "Species of Concern", "value": 72},
                {"name": "Threatened", "value": 6},
                {"name": "Under Review", "value": 12}
            ]
           },
           {
            "name": "Mammoth Cave National Park",
            "children": [
                {"name": "Endangered", "value": 13},
                {"name": "In Recovery", "value": 2},
                {"name": "No Concern", "value": 2418},
               
                {"name": "Species of Concern", "value": 53},
                {"name": "Threatened", "value": 1},
                {"name": "Under Review", "value": 12}
            ]
           }
      ]
     }
     
    ]
   }
   